ftpdata/Directory.py
ftpdata/Instance.py
ftpdata/Navigator.py
ftpdata/QueryResult.py
ftpdata/__init__.py
ftpdata/create_engine.py
ftpdata/exceptions.py
ftpdata/util.py
testbench/MockSFTP/__init__.py
ftpdata-0.1.1.dist-info/LICENSE
ftpdata-0.1.1.dist-info/METADATA
ftpdata-0.1.1.dist-info/WHEEL
ftpdata-0.1.1.dist-info/top_level.txt
ftpdata-0.1.1.dist-info/RECORD
